restricted/__init__.py
restricted/core.py
restricted/exceptions.py
restricted/helpers.py
restricted/utils.py
restricted-0.2.1.dist-info/METADATA
restricted-0.2.1.dist-info/WHEEL
restricted-0.2.1.dist-info/licenses/LICENSE
restricted-0.2.1.dist-info/RECORD
