Metadata-Version: 2.4
Name: restricted
Version: 0.2.1
Summary: A lightweight Python package for analyzing and securely executing code blocks with AST-based restrictions.
Author: Bimal Paudel
License-File: LICENSE
Keywords: ast,exec,execution,interpreter,python,restricted,uv
Requires-Python: >=3.13
